{
"meta":{"test_sets":[],"test_metrics":[],"learn_metrics":[{"best_value":"Min","name":"RMSE"}],"launch_mode":"Train","parameters":"","iteration_count":100,"learn_sets":["learn"],"name":"experiment"},
"iterations":[
{"learn":[868631.2614],"iteration":0,"passed_time":0.002246098356,"remaining_time":0.2223637372},
{"learn":[856860.2677],"iteration":1,"passed_time":0.004220691196,"remaining_time":0.2068138686},
{"learn":[817102.5349],"iteration":2,"passed_time":0.005914455098,"remaining_time":0.1912340482},
{"learn":[806132.2951],"iteration":3,"passed_time":0.007022915686,"remaining_time":0.1685499765},
{"learn":[793824.8421],"iteration":4,"passed_time":0.008889699043,"remaining_time":0.1689042818},
{"learn":[759011.5295],"iteration":5,"passed_time":0.01073258772,"remaining_time":0.1681438742},
{"learn":[749149.3269],"iteration":6,"passed_time":0.01253898809,"remaining_time":0.1665894132},
{"learn":[718490.3364],"iteration":7,"passed_time":0.01387256034,"remaining_time":0.1595344439},
{"learn":[706799.993],"iteration":8,"passed_time":0.0155036897,"remaining_time":0.1567595292},
{"learn":[695438.1003],"iteration":9,"passed_time":0.01734006931,"remaining_time":0.1560606238},
{"learn":[685973.6746],"iteration":10,"passed_time":0.01867763783,"remaining_time":0.1511190697},
{"learn":[677443.4125],"iteration":11,"passed_time":0.02027307262,"remaining_time":0.1486691992},
{"learn":[669210.8669],"iteration":12,"passed_time":0.02203935562,"remaining_time":0.1474941491},
{"learn":[640610.1047],"iteration":13,"passed_time":0.02395888162,"remaining_time":0.1471759871},
{"learn":[630377.7624],"iteration":14,"passed_time":0.0256010828,"remaining_time":0.1450728025},
{"learn":[622749.803],"iteration":15,"passed_time":0.02671702845,"remaining_time":0.1402643994},
{"learn":[613847.8572],"iteration":16,"passed_time":0.02842684776,"remaining_time":0.1387899038},
{"learn":[583398.8329],"iteration":17,"passed_time":0.03007316451,"remaining_time":0.1369999717},
{"learn":[560862.6163],"iteration":18,"passed_time":0.03192683976,"remaining_time":0.136109159},
{"learn":[554122.0178],"iteration":19,"passed_time":0.03359664234,"remaining_time":0.1343865694},
{"learn":[547565.2475],"iteration":20,"passed_time":0.03539607247,"remaining_time":0.1331566536},
{"learn":[541682.5401],"iteration":21,"passed_time":0.03729793695,"remaining_time":0.1322381401},
{"learn":[520311.085],"iteration":22,"passed_time":0.03889885583,"remaining_time":0.1302266043},
{"learn":[512514.3059],"iteration":23,"passed_time":0.04006215867,"remaining_time":0.1268635024},
{"learn":[493033.6203],"iteration":24,"passed_time":0.04143697489,"remaining_time":0.1243109247},
{"learn":[487720.9515],"iteration":25,"passed_time":0.04335248196,"remaining_time":0.1233878333},
{"learn":[482490.5822],"iteration":26,"passed_time":0.04461265642,"remaining_time":0.1206194044},
{"learn":[465909.4971],"iteration":27,"passed_time":0.04666620212,"remaining_time":0.1199988054},
{"learn":[461152.7578],"iteration":28,"passed_time":0.04881640651,"remaining_time":0.1195160297},
{"learn":[441485.5904],"iteration":29,"passed_time":0.05061699057,"remaining_time":0.1181063113},
{"learn":[435610.6607],"iteration":30,"passed_time":0.05216827106,"remaining_time":0.1161164743},
{"learn":[420779.7175],"iteration":31,"passed_time":0.05410073856,"remaining_time":0.1149640694},
{"learn":[415137.5239],"iteration":32,"passed_time":0.05555044573,"remaining_time":0.1127842383},
{"learn":[411066.3487],"iteration":33,"passed_time":0.05738943176,"remaining_time":0.1114030146},
{"learn":[405901.6701],"iteration":34,"passed_time":0.05870978527,"remaining_time":0.1090324584},
{"learn":[402132.1587],"iteration":35,"passed_time":0.05983139662,"remaining_time":0.1063669273},
{"learn":[389258.8675],"iteration":36,"passed_time":0.06119009013,"remaining_time":0.1041885318},
{"learn":[385731.4665],"iteration":37,"passed_time":0.06310132268,"remaining_time":0.1029547896},
{"learn":[382333.6208],"iteration":38,"passed_time":0.06502954166,"remaining_time":0.1017128729},
{"learn":[366609.6987],"iteration":39,"passed_time":0.06701839854,"remaining_time":0.1005275978},
{"learn":[362273.3757],"iteration":40,"passed_time":0.06862174757,"remaining_time":0.09874836845},
{"learn":[350262.0452],"iteration":41,"passed_time":0.07067323965,"remaining_time":0.09759637856},
{"learn":[347237.104],"iteration":42,"passed_time":0.07262851688,"remaining_time":0.09627501074},
{"learn":[344831.0499],"iteration":43,"passed_time":0.07485248427,"remaining_time":0.09526679816},
{"learn":[341957.3509],"iteration":44,"passed_time":0.07672406562,"remaining_time":0.09377385798},
{"learn":[339255.5662],"iteration":45,"passed_time":0.07861235949,"remaining_time":0.09228407419},
{"learn":[327752.2848],"iteration":46,"passed_time":0.08065329891,"remaining_time":0.09094946473},
{"learn":[325286.8968],"iteration":47,"passed_time":0.08247493598,"remaining_time":0.08934784731},
{"learn":[315559.2571],"iteration":48,"passed_time":0.08446294282,"remaining_time":0.08791040987},
{"learn":[308254.897],"iteration":49,"passed_time":0.08635374982,"remaining_time":0.08635374982},
{"learn":[306026.5622],"iteration":50,"passed_time":0.08828024973,"remaining_time":0.08481827915},
{"learn":[300885.3351],"iteration":51,"passed_time":0.09003230001,"remaining_time":0.08310673847},
{"learn":[298831.0669],"iteration":52,"passed_time":0.09171161227,"remaining_time":0.0813291656},
{"learn":[296853.4756],"iteration":53,"passed_time":0.09382931964,"remaining_time":0.0799286797},
{"learn":[287616.8268],"iteration":54,"passed_time":0.09603781842,"remaining_time":0.07857639689},
{"learn":[286025.3882],"iteration":55,"passed_time":0.0971638249,"remaining_time":0.07634300528},
{"learn":[284253.5784],"iteration":56,"passed_time":0.09916924301,"remaining_time":0.07481188508},
{"learn":[282825.012],"iteration":57,"passed_time":0.1002782124,"remaining_time":0.07261525727},
{"learn":[275275.0531],"iteration":58,"passed_time":0.1021433987,"remaining_time":0.07098100586},
{"learn":[271403.2944],"iteration":59,"passed_time":0.1040331617,"remaining_time":0.06935544113},
{"learn":[263245.091],"iteration":60,"passed_time":0.1061664157,"remaining_time":0.0678768887},
{"learn":[260809.5816],"iteration":61,"passed_time":0.108000804,"remaining_time":0.06619404113},
{"learn":[259357.2427],"iteration":62,"passed_time":0.1103206536,"remaining_time":0.064791495},
{"learn":[257293.9418],"iteration":63,"passed_time":0.111778498,"remaining_time":0.06287540511},
{"learn":[255993.184],"iteration":64,"passed_time":0.1133150266,"remaining_time":0.06101578355},
{"learn":[250527.862],"iteration":65,"passed_time":0.1151163884,"remaining_time":0.0593023819},
{"learn":[248371.1538],"iteration":66,"passed_time":0.116736153,"remaining_time":0.0574969112},
{"learn":[242755.7123],"iteration":67,"passed_time":0.1187204392,"remaining_time":0.05586844197},
{"learn":[241799.0535],"iteration":68,"passed_time":0.1201194966,"remaining_time":0.05396673037},
{"learn":[240699.4524],"iteration":69,"passed_time":0.1219117076,"remaining_time":0.05224787469},
{"learn":[237619.7242],"iteration":70,"passed_time":0.1237888584,"remaining_time":0.05056164637},
{"learn":[236000.493],"iteration":71,"passed_time":0.1257661279,"remaining_time":0.04890904975},
{"learn":[230515.5822],"iteration":72,"passed_time":0.1278466363,"remaining_time":0.04728574218},
{"learn":[229594.6616],"iteration":73,"passed_time":0.1298458719,"remaining_time":0.04562152254},
{"learn":[228174.6851],"iteration":74,"passed_time":0.1319766217,"remaining_time":0.04399220723},
{"learn":[222638.756],"iteration":75,"passed_time":0.1339610491,"remaining_time":0.04230348919},
{"learn":[221843.9574],"iteration":76,"passed_time":0.1356587573,"remaining_time":0.04052144698},
{"learn":[219985.0545],"iteration":77,"passed_time":0.1379157279,"remaining_time":0.03889930786},
{"learn":[218173.1844],"iteration":78,"passed_time":0.139592685,"remaining_time":0.03710691625},
{"learn":[217017.1483],"iteration":79,"passed_time":0.1413597144,"remaining_time":0.03533992859},
{"learn":[215884.7524],"iteration":80,"passed_time":0.1436884913,"remaining_time":0.03370470783},
{"learn":[211684.4153],"iteration":81,"passed_time":0.1454770269,"remaining_time":0.03193398151},
{"learn":[206580.0889],"iteration":82,"passed_time":0.1473075119,"remaining_time":0.03017141809},
{"learn":[203988.2722],"iteration":83,"passed_time":0.149389551,"remaining_time":0.02845515256},
{"learn":[203420.4589],"iteration":84,"passed_time":0.1510843345,"remaining_time":0.02666194138},
{"learn":[202914.8245],"iteration":85,"passed_time":0.15313463,"remaining_time":0.02492889326},
{"learn":[200415.919],"iteration":86,"passed_time":0.1555159926,"remaining_time":0.02323802189},
{"learn":[199972.7974],"iteration":87,"passed_time":0.156304274,"remaining_time":0.02131421918},
{"learn":[197342.5656],"iteration":88,"passed_time":0.1582376605,"remaining_time":0.01955746366},
{"learn":[195351.6792],"iteration":89,"passed_time":0.1600155131,"remaining_time":0.01777950146},
{"learn":[194225.9211],"iteration":90,"passed_time":0.1616336743,"remaining_time":0.01598574801},
{"learn":[192275.0791],"iteration":91,"passed_time":0.1631818339,"remaining_time":0.01418972469},
{"learn":[190035.4766],"iteration":92,"passed_time":0.1645724343,"remaining_time":0.01238717247},
{"learn":[187872.6351],"iteration":93,"passed_time":0.1667510195,"remaining_time":0.0106436821},
{"learn":[185471.9684],"iteration":94,"passed_time":0.1686024109,"remaining_time":0.008873811099},
{"learn":[184842.7105],"iteration":95,"passed_time":0.1700028842,"remaining_time":0.007083453507},
{"learn":[184438.4892],"iteration":96,"passed_time":0.1718601265,"remaining_time":0.005315261645},
{"learn":[184069.7659],"iteration":97,"passed_time":0.1736874419,"remaining_time":0.003544641672},
{"learn":[180135.8345],"iteration":98,"passed_time":0.175410406,"remaining_time":0.001771822283},
{"learn":[179753.3544],"iteration":99,"passed_time":0.1771550186,"remaining_time":0}
]}